[{"customFade":"circle","x":0,"scrollY":0,"lightingTo":0.05,"__name":"SJ2021/LightingMask","height":24,"id":8190,"y":112,"addBase":true,"width":16,"flag":"","fade":"None","lightingFrom":-1,"notFlag":false,"scrollX":0},{"__name":"FrostHelper/StaticDoor","height":16,"closeSfx":"","lightOccludeAlpha":1,"id":8191,"x":15,"openSfx":"","width":16,"type":"train","y":136},{"customFade":"circle","x":16,"scrollY":0,"lightingTo":0.05,"__name":"SJ2021/LightingMask","height":80,"id":8192,"y":56,"addBase":true,"width":256,"flag":"","fade":"None","lightingFrom":-1,"notFlag":false,"scrollX":0},{"__name":"SJ2021/TheoRespawn","flag":"","id":8193,"x":40,"y":136},{"__name":"player","id":8194,"x":40,"y":136},{"customFade":"circle","x":272,"scrollY":0,"lightingTo":0.05,"__name":"SJ2021/LightingMask","height":40,"id":8201,"y":96,"addBase":true,"width":32,"flag":"","fade":"None","lightingFrom":-1,"notFlag":false,"scrollX":0},{"startFade":48,"__name":"LunaticHelper/InvisibleLightSource","endFade":88,"alpha":0.8,"id":8202,"radius":88,"color":"White","x":72,"y":72},{"startFade":48,"__name":"LunaticHelper/InvisibleLightSource","endFade":88,"alpha":0.8,"id":8203,"radius":88,"color":"White","x":216,"y":72},{"__name":"spinner","id":8175,"x":300,"color":"Rainbow","attachToSolid":false,"y":136},{"__name":"spinner","id":8179,"x":308,"color":"Rainbow","attachToSolid":false,"y":136},{"left":true,"__name":"MaxHelpingHand/OneWayInvisibleBarrierHorizontal","letSeekersThrough":false,"height":8,"id":8207,"x":292,"y":128},{"__name":"MaxHelpingHand/SetFlagOnSpawnController","onlyOnRespawn":false,"flag":"solex_over","ifFlag":"","enable":false,"id":8210,"x":160,"y":104},{"noGhostSprite":true,"requireDashToBreak":true,"__name":"CollabUtils2/MiniHeart","particleColor":"","id":8211,"x":368,"sprite":"grandmaster","refillDash":true,"playPulseSound":true,"y":122},{"__children":[{"__name":"node","x":400,"y":128},{"__name":"node","x":270,"y":114}],"easing":"CubeOut","canReturn":true,"shakeTime":0.2,"x":360,"activeColor":"FFFFFF","iconVisible":false,"staticFit":false,"forceStandardBehavior":false,"playSounds":false,"__name":"EeveeHelper/FlagGateContainer","height":16,"icon":"objects/switchgate/icon","id":8212,"containMode":"RoomStart","inactiveColor":"5FCDE4","y":114,"blacklist":"","finishColor":"F141DF","width":16,"moveTime":2,"containFlag":"","ignoreAnchors":false,"whitelist":"","fitContained":true,"moveFlag":"solex_over"},{"__name":"SJ2021/TheoRespawn","flag":"","id":8213,"x":232,"y":136},{"__name":"player","id":8214,"x":232,"y":136},{"left":true,"__name":"MaxHelpingHand/OneWayInvisibleBarrierHorizontal","letSeekersThrough":false,"height":40,"id":8215,"x":291,"y":48},{"__children":[{"__name":"node","x":331,"y":86},{"__name":"node","x":291,"y":96}],"easing":"CubeOut","canReturn":true,"shakeTime":0,"x":291,"activeColor":"FFFFFF","iconVisible":false,"staticFit":false,"forceStandardBehavior":false,"playSounds":false,"__name":"EeveeHelper/FlagGateContainer","height":40,"icon":"objects/switchgate/icon","id":8218,"containMode":"RoomStart","inactiveColor":"5FCDE4","y":48,"blacklist":"","finishColor":"F141DF","width":8,"moveTime":0,"containFlag":"","ignoreAnchors":false,"whitelist":"","fitContained":true,"moveFlag":"solex_over"},{"__name":"MaxHelpingHand/StylegroundFadeController","flag":"solar_FGasteroids","fadeInTime":0.5,"id":652,"x":304,"notFlag":false,"fadeOutTime":0.5,"y":176},{"bloomAlpha":0.3,"x":272,"lightColor":"FFFFFF","bloomBlacklist":"","__name":"SJ2021/GlowController","bloomOffsetY":-8,"id":678,"lightOffsetX":0,"y":176,"lightEndFade":48,"lightStartFade":24,"lightOffsetY":0,"bloomRadius":8,"lightWhitelist":"","lightAlpha":1,"bloomWhitelist":"Celeste.TheoCrystal","bloomOffsetX":0,"lightBlacklist":"Celeste.TheoCrystal"},{"bloomAlpha":1,"x":248,"lightColor":"F9B343","bloomBlacklist":"","__name":"SJ2021/GlowController","bloomOffsetY":-8,"id":738,"lightOffsetX":0,"y":176,"lightEndFade":36,"lightStartFade":18,"lightOffsetY":-8,"bloomRadius":8,"lightWhitelist":"Celeste.TheoCrystal","lightAlpha":1,"bloomWhitelist":"","bloomOffsetX":0,"lightBlacklist":""}]